README.txt
setup.cfg
setup.py
docs/HISTORY.txt
docs/INSTALL.txt
docs/LICENSE.txt
sk/__init__.py
sk.recipe.xdv.egg-info/PKG-INFO
sk.recipe.xdv.egg-info/SOURCES.txt
sk.recipe.xdv.egg-info/dependency_links.txt
sk.recipe.xdv.egg-info/entry_points.txt
sk.recipe.xdv.egg-info/namespace_packages.txt
sk.recipe.xdv.egg-info/requires.txt
sk.recipe.xdv.egg-info/top_level.txt
sk.recipe.xdv.egg-info/zip-safe
sk/recipe/__init__.py
sk/recipe/xdv/README.txt
sk/recipe/xdv/__init__.py
sk/recipe/xdv/impl.py
sk/recipe/xdv/tests.py
sk/recipe/xdv/testdata/morerules.xml
sk/recipe/xdv/testdata/rules.xml
sk/recipe/xdv/testdata/theme.html